{
  "main": {
    "id": "bcd8205a1729e37c",
    "type": "split",
    "children": [
      {
        "id": "5b60ed7d76489ea5",
        "type": "tabs",
        "children": [
          {
            "id": "a635e3366c8b796b",
            "type": "leaf",
            "state": {
              "type": "markdown",
              "state": {
                "file": "UCSC/CSE150/Network Layer.md",
                "mode": "source",
                "source": false
              },
              "icon": "lucide-file",
              "title": "Network Layer"
            }
          }
        ]
      }
    ],
    "direction": "vertical"
  },
  "left": {
    "id": "464371168d32d7e0",
    "type": "split",
    "children": [
      {
        "id": "5f5197af22ba7b59",
        "type": "tabs",
        "children": [
          {
            "id": "a48deccce47eeef1",
            "type": "leaf",
            "state": {
              "type": "file-explorer",
              "state": {
                "sortOrder": "alphabetical",
                "autoReveal": false
              },
              "icon": "lucide-folder-closed",
              "title": "Files"
            }
          },
          {
            "id": "26db5c248f4afa05",
            "type": "leaf",
            "state": {
              "type": "search",
              "state": {
                "query": "",
                "matchingCase": false,
                "explainSearch": false,
                "collapseAll": false,
                "extraContext": false,
                "sortOrder": "alphabetical"
              },
              "icon": "lucide-search",
              "title": "Search"
            }
          },
          {
            "id": "c2d65670fc83e04a",
            "type": "leaf",
            "state": {
              "type": "bookmarks",
              "state": {},
              "icon": "lucide-bookmark",
              "title": "Bookmarks"
            }
          }
        ]
      }
    ],
    "direction": "horizontal",
    "width": 300
  },
  "right": {
    "id": "b09449b3501a57fa",
    "type": "split",
    "children": [
      {
        "id": "f240526a16e67594",
        "type": "tabs",
        "children": [
          {
            "id": "b2af020b392c64ca",
            "type": "leaf",
            "state": {
              "type": "backlink",
              "state": {
                "file": "Self Study/Distributed Systems/Distributed Systems Learning.md",
                "collapseAll": false,
                "extraContext": false,
                "sortOrder": "alphabetical",
                "showSearch": false,
                "searchQuery": "",
                "backlinkCollapsed": false,
                "unlinkedCollapsed": true
              },
              "icon": "links-coming-in",
              "title": "Backlinks for Distributed Systems Learning"
            }
          },
          {
            "id": "ab0542caa79ede55",
            "type": "leaf",
            "state": {
              "type": "outgoing-link",
              "state": {
                "file": "Self Study/Distributed Systems/Distributed Systems Learning.md",
                "linksCollapsed": false,
                "unlinkedCollapsed": true
              },
              "icon": "links-going-out",
              "title": "Outgoing links from Distributed Systems Learning"
            }
          },
          {
            "id": "6351d90f9e5aa71e",
            "type": "leaf",
            "state": {
              "type": "tag",
              "state": {
                "sortOrder": "frequency",
                "useHierarchy": true,
                "showSearch": false,
                "searchQuery": ""
              },
              "icon": "lucide-tags",
              "title": "Tags"
            }
          },
          {
            "id": "3ccab7d5f7ac212a",
            "type": "leaf",
            "state": {
              "type": "outline",
              "state": {
                "file": "Self Study/Distributed Systems/Distributed Systems Learning.md",
                "followCursor": false,
                "showSearch": false,
                "searchQuery": ""
              },
              "icon": "lucide-list",
              "title": "Outline of Distributed Systems Learning"
            }
          }
        ]
      }
    ],
    "direction": "horizontal",
    "width": 300,
    "collapsed": true
  },
  "left-ribbon": {
    "hiddenItems": {
      "switcher:Open quick switcher": false,
      "graph:Open graph view": false,
      "canvas:Create new canvas": false,
      "daily-notes:Open today's daily note": false,
      "templates:Insert template": false,
      "command-palette:Open command palette": false
    }
  },
  "active": "a635e3366c8b796b",
  "lastOpenFiles": [
    "et.md",
    "UCSC/CSE150/Network Layer.md",
    "UCSC/CSE150/Transport Layer.md",
    "UCSC/CSE150/Application Layer.md",
    "Self Study/Istio/Istio Links.md",
    "Self Study/Istio/Istio CRDs.md",
    "Self Study/Istio/Istioctl.md",
    "Self Study/Istio/Istio Components.md",
    "Self Study/Istio/Service Mesh Introduction.md",
    "Self Study/Kubernetes/Kubernetes Components.md",
    "Images/Pasted image 20250520090051.png",
    "UCSC/CSE182/SQL.md",
    "Images/Pasted image 20250520090203.png",
    "Images/Pasted image 20250520110832.png",
    "Images/Pasted image 20250520110810.png",
    "Images/Pasted image 20250520110754.png",
    "Images/Pasted image 20250520110657.png",
    "Images/Pasted image 20250520110421.png",
    "Images/Pasted image 20250520101857.png",
    "Images/Pasted image 20250520101605.png",
    "Images/Pasted image 20250520091135.png",
    "UCSC/CSE114A/Haskell.md",
    "UCSC/CSE114A/Elsa.md",
    "UCSC/CSE114A/Lambda Calculus.md",
    "UCSC/CSE114A/Logistics.md",
    "UCSC/CSE150/Introduction.md",
    "UCSC/CSE182/Lock In.md",
    "UCSC/CSE182/General Review.md",
    "UCSC/CSE182/The Relational Data Model.md",
    "UCSC/CSE182/Practice Homeworks.md",
    "UCSC/CSE182/Introduction.md",
    "UCSC/CSE150/Logistics.md",
    "misc/create a link.md",
    "misc/Welcome.md",
    "Self Study/AI Agents/NVIDIA AI Agent Workshop TiECon 2025.md",
    "UCSC/CSE114A/Introduction.md",
    "Untitled.canvas",
    "Images",
    "Self Study/Kubernetes/Untitled",
    "UCSC/CSE150",
    "UCSC/CSE114A/Untitled",
    "UCSC/CSE182",
    "UCSC/CSE114A",
    "UCSC",
    "Self Study/SRE",
    "Self Study/AI Agents",
    "Self Study/Istio"
  ]
}